{
  "_format": "hh-sol-cache-2",
  "files": {
    "/mnt/c/Users/maarb/Desktop/PRUEBA_INFUY/SC/contracts/Signature.sol": {
      "lastModificationDate": 1663602243659,
      "contentHash": "2809ed98d28affee8bcceb9c166def71",
      "sourceName": "contracts/Signature.sol",
      "solcConfig": {
        "version": "0.8.17",
        "settings": {
          "optimizer": {
            "enabled": false,
            "runs": 200
          },
          "outputSelection": {
            "*": {
              "*": [
                "abi",
                "evm.bytecode",
                "evm.deployedBytecode",
                "evm.methodIdentifiers",
                "metadata"
              ],
              "": [
                "ast"
              ]
            }
          }
        }
      },
      "imports": [],
      "versionPragmas": [
        "^0.8.13"
      ],
      "artifacts": [
        "Signature"
      ]
    },
    "/mnt/c/Users/maarb/Desktop/PRUEBA_INFUY/SC/contracts/Staking.sol": {
      "lastModificationDate": 1663724061721,
      "contentHash": "25dc75680b6e0f4b16eb4366bd3a4c52",
      "sourceName": "contracts/Staking.sol",
      "solcConfig": {
        "version": "0.8.17",
        "settings": {
          "optimizer": {
            "enabled": false,
            "runs": 200
          },
          "outputSelection": {
            "*": {
              "*": [
                "abi",
                "evm.bytecode",
                "evm.deployedBytecode",
                "evm.methodIdentifiers",
                "metadata"
              ],
              "": [
                "ast"
              ]
            }
          }
        }
      },
      "imports": [
        "@openzeppelin/contracts/access/Ownable.sol",
        "@openzeppelin/contracts/token/ERC20/IERC20.sol"
      ],
      "versionPragmas": [
        "^0.8.0"
      ],
      "artifacts": [
        "Staking"
      ]
    },
    "/mnt/c/Users/maarb/Desktop/PRUEBA_INFUY/SC/node_modules/@openzeppelin/contracts/access/Ownable.sol": {
      "lastModificationDate": 1663602317028,
      "contentHash": "e436cea06129be2c73cda4b1acc848b5",
      "sourceName": "@openzeppelin/contracts/access/Ownable.sol",
      "solcConfig": {
        "version": "0.8.17",
        "settings": {
          "optimizer": {
            "enabled": false,
            "runs": 200
          },
          "outputSelection": {
            "*": {
              "*": [
                "abi",
                "evm.bytecode",
                "evm.deployedBytecode",
                "evm.methodIdentifiers",
                "metadata"
              ],
              "": [
                "ast"
              ]
            }
          }
        }
      },
      "imports": [
        "../utils/Context.sol"
      ],
      "versionPragmas": [
        "^0.8.0"
      ],
      "artifacts": [
        "Ownable"
      ]
    },
    "/mnt/c/Users/maarb/Desktop/PRUEBA_INFUY/SC/node_modules/@openzeppelin/contracts/token/ERC20/IERC20.sol": {
      "lastModificationDate": 1663602316935,
      "contentHash": "ad7c2d0af148c8f9f097d65deeb4da6b",
      "sourceName": "@openzeppelin/contracts/token/ERC20/IERC20.sol",
      "solcConfig": {
        "version": "0.8.17",
        "settings": {
          "optimizer": {
            "enabled": false,
            "runs": 200
          },
          "outputSelection": {
            "*": {
              "*": [
                "abi",
                "evm.bytecode",
                "evm.deployedBytecode",
                "evm.methodIdentifiers",
                "metadata"
              ],
              "": [
                "ast"
              ]
            }
          }
        }
      },
      "imports": [],
      "versionPragmas": [
        "^0.8.0"
      ],
      "artifacts": [
        "IERC20"
      ]
    },
    "/mnt/c/Users/maarb/Desktop/PRUEBA_INFUY/SC/node_modules/@openzeppelin/contracts/utils/Context.sol": {
      "lastModificationDate": 1663602316383,
      "contentHash": "5f2c5c4b6af2dd4551027144797bc8be",
      "sourceName": "@openzeppelin/contracts/utils/Context.sol",
      "solcConfig": {
        "version": "0.8.17",
        "settings": {
          "optimizer": {
            "enabled": false,
            "runs": 200
          },
          "outputSelection": {
            "*": {
              "*": [
                "abi",
                "evm.bytecode",
                "evm.deployedBytecode",
                "evm.methodIdentifiers",
                "metadata"
              ],
              "": [
                "ast"
              ]
            }
          }
        }
      },
      "imports": [],
      "versionPragmas": [
        "^0.8.0"
      ],
      "artifacts": [
        "Context"
      ]
    },
    "/mnt/c/Users/maarb/Desktop/PRUEBA_INFUY/SC/node_modules/@openzeppelin/contracts/token/ERC20/extensions/IERC20Metadata.sol": {
      "lastModificationDate": 1663602316938,
      "contentHash": "909ab67fc5c25033fe6cd364f8c056f9",
      "sourceName": "@openzeppelin/contracts/token/ERC20/extensions/IERC20Metadata.sol",
      "solcConfig": {
        "version": "0.8.17",
        "settings": {
          "optimizer": {
            "enabled": false,
            "runs": 200
          },
          "outputSelection": {
            "*": {
              "*": [
                "abi",
                "evm.bytecode",
                "evm.deployedBytecode",
                "evm.methodIdentifiers",
                "metadata"
              ],
              "": [
                "ast"
              ]
            }
          }
        }
      },
      "imports": [
        "../IERC20.sol"
      ],
      "versionPragmas": [
        "^0.8.0"
      ],
      "artifacts": [
        "IERC20Metadata"
      ]
    },
    "/mnt/c/Users/maarb/Desktop/PRUEBA_INFUY/SC/node_modules/@openzeppelin/contracts/token/ERC20/ERC20.sol": {
      "lastModificationDate": 1663602316735,
      "contentHash": "af7bd64e1cfefbf6cb07f2adc1a25392",
      "sourceName": "@openzeppelin/contracts/token/ERC20/ERC20.sol",
      "solcConfig": {
        "version": "0.8.17",
        "settings": {
          "optimizer": {
            "enabled": false,
            "runs": 200
          },
          "outputSelection": {
            "*": {
              "*": [
                "abi",
                "evm.bytecode",
                "evm.deployedBytecode",
                "evm.methodIdentifiers",
                "metadata"
              ],
              "": [
                "ast"
              ]
            }
          }
        }
      },
      "imports": [
        "./IERC20.sol",
        "./extensions/IERC20Metadata.sol",
        "../../utils/Context.sol"
      ],
      "versionPragmas": [
        "^0.8.0"
      ],
      "artifacts": [
        "ERC20"
      ]
    },
    "/mnt/c/Users/maarb/Desktop/PRUEBA_INFUY/SC/contracts/campaign/CampaignSale.sol": {
      "lastModificationDate": 1664197365493,
      "contentHash": "976a870d9d5ddbe633e7b5d0789d1f82",
      "sourceName": "contracts/campaign/CampaignSale.sol",
      "solcConfig": {
        "version": "0.8.17",
        "settings": {
          "optimizer": {
            "enabled": false,
            "runs": 200
          },
          "outputSelection": {
            "*": {
              "*": [
                "abi",
                "evm.bytecode",
                "evm.deployedBytecode",
                "evm.methodIdentifiers",
                "metadata"
              ],
              "": [
                "ast"
              ]
            }
          }
        }
      },
      "imports": [
        "@openzeppelin/contracts/utils/Counters.sol",
        "@openzeppelin/contracts/token/ERC20/IERC20.sol",
        "@openzeppelin/contracts/access/Ownable.sol",
        "../interfaces/ICampaignSale.sol"
      ],
      "versionPragmas": [
        "^0.8.13"
      ],
      "artifacts": [
        "CampaignSale"
      ]
    },
    "/mnt/c/Users/maarb/Desktop/PRUEBA_INFUY/SC/contracts/interfaces/ICampaignSale.sol": {
      "lastModificationDate": 1664196846927,
      "contentHash": "0851b256a9d5250016b1bbbce55758dd",
      "sourceName": "contracts/interfaces/ICampaignSale.sol",
      "solcConfig": {
        "version": "0.8.17",
        "settings": {
          "optimizer": {
            "enabled": false,
            "runs": 200
          },
          "outputSelection": {
            "*": {
              "*": [
                "abi",
                "evm.bytecode",
                "evm.deployedBytecode",
                "evm.methodIdentifiers",
                "metadata"
              ],
              "": [
                "ast"
              ]
            }
          }
        }
      },
      "imports": [],
      "versionPragmas": [
        "^0.8.13"
      ],
      "artifacts": [
        "ICampaignSale"
      ]
    },
    "/mnt/c/Users/maarb/Desktop/PRUEBA_INFUY/SC/node_modules/@openzeppelin/contracts/utils/Counters.sol": {
      "lastModificationDate": 1663602316387,
      "contentHash": "74654e3ae5d7f39555055dfe244dab7a",
      "sourceName": "@openzeppelin/contracts/utils/Counters.sol",
      "solcConfig": {
        "version": "0.8.17",
        "settings": {
          "optimizer": {
            "enabled": false,
            "runs": 200
          },
          "outputSelection": {
            "*": {
              "*": [
                "abi",
                "evm.bytecode",
                "evm.deployedBytecode",
                "evm.methodIdentifiers",
                "metadata"
              ],
              "": [
                "ast"
              ]
            }
          }
        }
      },
      "imports": [],
      "versionPragmas": [
        "^0.8.0"
      ],
      "artifacts": [
        "Counters"
      ]
    },
    "/mnt/c/Users/maarb/Desktop/PRUEBA_INFUY/SC/contracts/test/ERC20Test.sol": {
      "lastModificationDate": 1663631748262,
      "contentHash": "621c93ba77cabaa40936e34d48cbe367",
      "sourceName": "contracts/test/ERC20Test.sol",
      "solcConfig": {
        "version": "0.8.17",
        "settings": {
          "optimizer": {
            "enabled": false,
            "runs": 200
          },
          "outputSelection": {
            "*": {
              "*": [
                "abi",
                "evm.bytecode",
                "evm.deployedBytecode",
                "evm.methodIdentifiers",
                "metadata"
              ],
              "": [
                "ast"
              ]
            }
          }
        }
      },
      "imports": [
        "@openzeppelin/contracts/token/ERC20/ERC20.sol",
        "@openzeppelin/contracts/utils/math/SafeMath.sol"
      ],
      "versionPragmas": [
        "^0.8.13"
      ],
      "artifacts": [
        "ERC20TestToken"
      ]
    },
    "/mnt/c/Users/maarb/Desktop/PRUEBA_INFUY/SC/node_modules/@openzeppelin/contracts/utils/math/SafeMath.sol": {
      "lastModificationDate": 1663602317072,
      "contentHash": "2337f0279507b5edf14a07067adf0d05",
      "sourceName": "@openzeppelin/contracts/utils/math/SafeMath.sol",
      "solcConfig": {
        "version": "0.8.17",
        "settings": {
          "optimizer": {
            "enabled": false,
            "runs": 200
          },
          "outputSelection": {
            "*": {
              "*": [
                "abi",
                "evm.bytecode",
                "evm.deployedBytecode",
                "evm.methodIdentifiers",
                "metadata"
              ],
              "": [
                "ast"
              ]
            }
          }
        }
      },
      "imports": [],
      "versionPragmas": [
        "^0.8.0"
      ],
      "artifacts": [
        "SafeMath"
      ]
    }
  }
}
